musiclang_predict/__init__.py
musiclang_predict/predictors/__init__.py
musiclang_predict/predictors/transformer.py
musiclang_predict/tokenizers/__init__.py
musiclang_predict/tokenizers/bpe_iterator.py
musiclang_predict/tokenizers/bpe_tokenizer.py
musiclang_predict/tokenizers/chord_tokenizer.py
musiclang_predict/tokenizers/interceptor.py
musiclang_predict/tokenizers/template_extractor.py
musiclang_predict/tokenizers/tokenizer.py
tests/__init__.py
tests/test_tokenizer.py
musiclang_predict-0.5.0.dist-info/LICENSE
musiclang_predict-0.5.0.dist-info/METADATA
musiclang_predict-0.5.0.dist-info/WHEEL
musiclang_predict-0.5.0.dist-info/top_level.txt
musiclang_predict-0.5.0.dist-info/RECORD
