Metadata-Version: 2.1
Name: musiclang-predict
Version: 0.5.0
Summary: A python package for music notation and generation
Author: Florian GARDIN
Author-email: Florian GARDIN <fgardin.pro@gmail.com>
Project-URL: Homepage, https://github.com/MusicLang/musiclang_predict
Keywords: music,ai,notation
Classifier: License :: OSI Approved :: BSD License
Classifier: Programming Language :: Python
Classifier: Programming Language :: Python :: 3
Requires-Python: >=3.6
License-File: LICENSE
Requires-Dist: musiclang >=0.23
Requires-Dist: torch
Requires-Dist: transformers
Requires-Dist: tokenizers
Requires-Dist: torchtoolkit
Requires-Dist: accelerate
Provides-Extra: dev
Requires-Dist: pip-tools ; extra == 'dev'
Requires-Dist: pytest ; extra == 'dev'
